palindrome/__init__.py
palindrome/checker.py
palindrome/main__.py
palindromecheckerlib-0.1.0.dist-info/licenses/LICENSE
palindromecheckerlib-0.1.0.dist-info/METADATA
palindromecheckerlib-0.1.0.dist-info/WHEEL
palindromecheckerlib-0.1.0.dist-info/entry_points.txt
palindromecheckerlib-0.1.0.dist-info/top_level.txt
palindromecheckerlib-0.1.0.dist-info/RECORD
