Metadata-Version: 2.4
Name: PalindromeCheckerLib
Version: 0.1.0
Summary: Check if text is a palindrome
Author: Ali Alsheikh
Author-email: Ali Alsheikh <a77561289@gmail.com>
License: 
Project-URL: Homepage, https://pypi.org/project/PalindromeCheckerLib/
Requires-Python: >=3.13
License-File: LICENSE
Dynamic: author
Dynamic: license-file
Dynamic: requires-python
